context_engine/__init__.py
context_engine/error_analysis.py
context_engine/execution.py
context_engine/inspection_script.py
context_engine/license.py
context_engine/license_validator.py
context_engine/models.py
context_engine/notebook_manager.py
context_engine/notebook_manager_snippet.py
context_engine/outline_tool.py
context_engine/safety.py
context_engine/server.py
context_engine/token_manager.py
context_engine/profiles/__init__.py
context_engine/profiles/base.py
context_engine/profiles/finance.py
context_engine/profiles/ml.py
jupyters_server-0.1.8.dist-info/METADATA
jupyters_server-0.1.8.dist-info/WHEEL
jupyters_server-0.1.8.dist-info/entry_points.txt
jupyters_server-0.1.8.dist-info/RECORD
