Metadata-Version: 2.4
Name: jupyters-server
Version: 0.1.8
Summary: Commercial-grade Jupyter MCP server - Give your AI assistant superpowers with notebooks
Project-URL: Homepage, https://jupyters.fun
Project-URL: Documentation, https://jupyters.fun/docs
Project-URL: Repository, https://github.com/michaluppal/Jupyters
Project-URL: Pricing, https://jupyters.fun/pricing
Project-URL: Issues, https://github.com/michaluppal/Jupyters/issues
Author-email: Jupyters Team <support@jupyters.fun>
License: Commercial
Keywords: ai,claude,jupyter,llm,mcp,model-context-protocol,notebook
Classifier: Development Status :: 4 - Beta
Classifier: Intended Audience :: Developers
Classifier: Intended Audience :: Science/Research
Classifier: Programming Language :: Python :: 3
Classifier: Programming Language :: Python :: 3.10
Classifier: Programming Language :: Python :: 3.11
Classifier: Programming Language :: Python :: 3.12
Classifier: Topic :: Scientific/Engineering
Classifier: Topic :: Software Development
Requires-Python: >=3.10
Requires-Dist: ipykernel>=6.29.0
Requires-Dist: jupyter-client>=8.6.0
Requires-Dist: mcp[cli]>=1.0.0
Requires-Dist: nbformat>=5.10.0
Requires-Dist: pandas>=2.2.0
Requires-Dist: pydantic>=2.0.0
